<apam xmlns="fr.imag.adele.apam" xmlns:ipojo="org.apache.felix.ipojo" xmlns:xsi="http://www.w3.org/2001/XMLSchema-instance"
	xsi:schemaLocation="fr.imag.adele.apam http://repository-apam.forge.cloudbees.com/release/schema/ApamCore.xsd">
	
	<implementation name="TextGui-Impl" 
	    classname="fr.imag.adele.apam.text.gui.impl.TextGuiImplementation">
		<callback onInit="started" onRemove="stopped"/>
		<definition name="name" type="string" field="name"/>
		<dependency field="hello"/>
	</implementation>

	<apam-instance name="TextGui-Inst" implementation="TextGui-Impl" >
		<property name="name" value="ApAM Gui Text"/>
	</apam-instance>
</apam>